[{"stopID":"239029","tripID":"NP44.1386.138.32.P.2.76980420","id":"FBCB4CD4-7E62-453C-9E13-A8342EA288BD","arrival":{"minute":10,"second":0,"hour":9},"dropOffType":0,"departure":{"minute":15,"second":0,"hour":9},"pickupType":0,"stopSequenceNumber":3},{"stopID":"239029","tripID":"NP44.1386.138.92.P.2.76980420","id":"F0677750-98CE-41F4-9277-A84D01F1385D","arrival":{"minute":10,"second":0,"hour":9},"dropOffType":0,"departure":{"minute":15,"second":0,"hour":9},"pickupType":0,"stopSequenceNumber":3},{"stopID":"239029","tripID":"NP44.1387.142.130.P.2.76921769","id":"4CC43ACB-5A8F-4FC1-B01E-984E08D3B498","arrival":{"minute":10,"second":0,"hour":9},"dropOffType":0,"departure":{"minute":15,"second":0,"hour":9},"pickupType":0,"stopSequenceNumber":3},{"stopID":"239029","tripID":"NP44.1389.130.124.P.2.77042358","id":"28949A99-E008-4D00-A1A5-42CC1EE7F335","arrival":{"minute":10,"second":0,"hour":9},"dropOffType":0,"departure":{"minute":15,"second":0,"hour":9},"pickupType":0,"stopSequenceNumber":3},{"stopID":"239029","tripID":"NP44.1390.130.130.P.2.77040543","id":"6426EFBF-1A32-416A-8797-0E5A7234530D","arrival":{"minute":10,"second":0,"hour":9},"dropOffType":0,"departure":{"minute":15,"second":0,"hour":9},"pickupType":0,"stopSequenceNumber":3},{"stopID":"239029","tripID":"NP44.1527.100.124.P.2.49071649","id":"9ABE4931-8AA6-4F23-8058-A3FEE584C82C","arrival":{"minute":10,"second":0,"hour":9},"dropOffType":0,"departure":{"minute":15,"second":0,"hour":9},"pickupType":0,"stopSequenceNumber":3},{"stopID":"239029","tripID":"NP44.1527.100.130.P.2.49071654","id":"AF493681-2CD1-45B4-B6B1-5E87AC54BF79","arrival":{"minute":10,"second":0,"hour":9},"dropOffType":0,"departure":{"minute":15,"second":0,"hour":9},"pickupType":0,"stopSequenceNumber":3},{"stopID":"239029","tripID":"NP44.1871.102.104.P.2.77961775","id":"12C3AAE8-DB6D-4977-BA69-CE1537FABEFB","arrival":{"minute":10,"second":0,"hour":9},"dropOffType":0,"departure":{"minute":15,"second":0,"hour":9},"pickupType":0,"stopSequenceNumber":3},{"stopID":"239029","tripID":"NP44.1871.102.16.P.2.77961775","id":"1E85FF48-47E7-474E-BA92-9777C977727D","arrival":{"minute":10,"second":0,"hour":9},"dropOffType":0,"departure":{"minute":15,"second":0,"hour":9},"pickupType":0,"stopSequenceNumber":3},{"stopID":"239029","tripID":"NP44.1871.102.4.P.2.77953484","id":"E342C030-66B5-4C78-96BA-EA573ECC0E13","arrival":{"minute":10,"second":0,"hour":9},"dropOffType":0,"departure":{"minute":15,"second":0,"hour":9},"pickupType":0,"stopSequenceNumber":3},{"stopID":"239029","tripID":"NP43.1386.138.124.P.2.76984503","id":"3DF38627-1830-48ED-A9B3-1055A257490F","arrival":{"minute":52,"second":0,"hour":16},"dropOffType":0,"departure":{"minute":56,"second":0,"hour":16},"pickupType":0,"stopSequenceNumber":6},{"stopID":"239029","tripID":"NP43.1387.142.130.P.2.76920391","id":"C8C4B579-B3E5-43F5-A46C-09FC52D0024B","arrival":{"minute":52,"second":0,"hour":16},"dropOffType":0,"departure":{"minute":56,"second":0,"hour":16},"pickupType":0,"stopSequenceNumber":6},{"stopID":"239029","tripID":"NP43.1389.130.124.P.2.77042434","id":"A4198FB9-1763-44D0-8732-70D8F3304E1C","arrival":{"minute":52,"second":0,"hour":16},"dropOffType":0,"departure":{"minute":56,"second":0,"hour":16},"pickupType":0,"stopSequenceNumber":6},{"stopID":"239029","tripID":"NP43.1390.130.130.P.2.77039337","id":"40FD5A57-9999-4105-AC64-108D2F5CEB34","arrival":{"minute":52,"second":0,"hour":16},"dropOffType":0,"departure":{"minute":56,"second":0,"hour":16},"pickupType":0,"stopSequenceNumber":6},{"stopID":"239029","tripID":"NP43.1527.100.124.P.2.49071639","id":"0D907900-CEC6-489E-9857-8A3230908CAD","arrival":{"minute":52,"second":0,"hour":16},"dropOffType":0,"departure":{"minute":56,"second":0,"hour":16},"pickupType":0,"stopSequenceNumber":5},{"stopID":"239029","tripID":"NP43.1527.100.130.P.2.49071646","id":"A5163D57-CD3F-4BA6-84F1-0EABE1AA58CB","arrival":{"minute":52,"second":0,"hour":16},"dropOffType":0,"departure":{"minute":56,"second":0,"hour":16},"pickupType":0,"stopSequenceNumber":5},{"stopID":"239029","tripID":"NP43.1871.102.120.P.2.77965280","id":"558FBB76-AE1C-46FC-9F4A-95234DD24579","arrival":{"minute":52,"second":0,"hour":16},"dropOffType":0,"departure":{"minute":56,"second":0,"hour":16},"pickupType":0,"stopSequenceNumber":6},{"stopID":"239029","tripID":"NP43.1871.102.4.P.2.77957491","id":"36FA0AEB-2D42-4859-B65C-9B302FAFFFB5","arrival":{"minute":52,"second":0,"hour":16},"dropOffType":0,"departure":{"minute":56,"second":0,"hour":16},"pickupType":0,"stopSequenceNumber":6}]